biosspheres/__init__.py
biosspheres/formulations/__init__.py
biosspheres/formulations/massmatrices.py
biosspheres/formulations/mtf/__init__.py
biosspheres/formulations/mtf/mtf.py
biosspheres/formulations/mtf/propertieschecks.py
biosspheres/formulations/mtf/reconstructions.py
biosspheres/formulations/mtf/righthands.py
biosspheres/formulations/mtf/solvertemplates.py
biosspheres/formulations/mtf/timecouplings/__init__.py
biosspheres/formulations/mtf/timecouplings/linearoperators.py
biosspheres/formulations/mtf/timecouplings/righthands.py
biosspheres/formulations/mtf/timecouplings/solvertemplates.py
biosspheres/helmholtz/__init__.py
biosspheres/helmholtz/crossinteractions.py
biosspheres/helmholtz/selfinteractions.py
biosspheres/laplace/__init__.py
biosspheres/laplace/crossinteractions.py
biosspheres/laplace/drawing.py
biosspheres/laplace/selfinteractions.py
biosspheres/miscella/__init__.py
biosspheres/miscella/extensions.py
biosspheres/miscella/forcouplings/__init__.py
biosspheres/miscella/forcouplings/currents.py
biosspheres/miscella/forcouplings/oderesolutions.py
biosspheres/miscella/harmonicex.py
biosspheres/miscella/mathfunctions.py
biosspheres/miscella/spherearrangements.py
biosspheres/quadratures/__init__.py
biosspheres/quadratures/sphere.py
biosspheres/utils/__init__.py
biosspheres/utils/auxindexes.py
biosspheres/utils/drawing.py
biosspheres/utils/validation/__init__.py
biosspheres/utils/validation/inputs.py
biosspheres-0.1.1a1.dist-info/LICENSE
biosspheres-0.1.1a1.dist-info/METADATA
biosspheres-0.1.1a1.dist-info/WHEEL
biosspheres-0.1.1a1.dist-info/RECORD
