Metadata-Version: 2.1
Name: biosspheres
Version: 0.1.1a1
Summary: Python package to obtain Helmholtz or Laplace boundary integral operator on spheres using spherical harmonics. It also implements the Multiple Traces Formulation to solve scattering transmission problems in an ensemble of spheres.
Home-page: https://github.com/iamartineza/biosspheres
License: BSD-3-Clause
Author: Isabel Martínez
Author-email: iamartinez@uc.cl
Requires-Python: >=3.9,<3.13
Classifier: License :: OSI Approved :: BSD License
Classifier: Programming Language :: Python :: 3
Classifier: Programming Language :: Python :: 3.9
Classifier: Programming Language :: Python :: 3.10
Classifier: Programming Language :: Python :: 3.11
Classifier: Programming Language :: Python :: 3.12
Provides-Extra: all
Provides-Extra: jupyter
Provides-Extra: plotting
Requires-Dist: ipykernel (>=6.0) ; extra == "jupyter" or extra == "all"
Requires-Dist: ipython (>=7.0) ; extra == "jupyter" or extra == "all"
Requires-Dist: jupyterlab (>=3.0) ; extra == "jupyter" or extra == "all"
Requires-Dist: matplotlib (>=3.8) ; extra == "plotting" or extra == "jupyter" or extra == "all"
Requires-Dist: notebook (>=7.2.2) ; extra == "jupyter" or extra == "all"
Requires-Dist: numpy (>=1.26.4)
Requires-Dist: pyshtools (>=4.10.4)
Requires-Dist: scipy (>=1.11.4,<1.14.0)
Project-URL: Repository, https://github.com/iamartineza/biosspheres
